atuproot/BEvents.py
atuproot/CollectorComposite.py
atuproot/EventBuilder.py
atuproot/EventBuilderConfigMaker.py
atuproot/EventDatasetReader.py
atuproot/ReaderComposite.py
atuproot/__init__.py
atuproot/atuproot_main.py
atuproot-0.3.0.dist-info/LICENSE
atuproot-0.3.0.dist-info/METADATA
atuproot-0.3.0.dist-info/WHEEL
atuproot-0.3.0.dist-info/top_level.txt
atuproot-0.3.0.dist-info/RECORD
